{
    "2001":{
        "id":2001,
        "OpenTime":"0",
        "CloseTime":"0"
    },
    "2002":{
        "id":2002,
        "OpenTime":"0",
        "CloseTime":"0"
    },
    "2003":{
        "id":2003,
        "OpenTime":"0",
        "CloseTime":"0"
    },
    "2004":{
        "id":2004,
        "OpenTime":"0",
        "CloseTime":"0"
    },
    "2007":{
        "id":2007,
        "OpenTime":"2021-01-14 04:00:00",
        "CloseTime":"2021-08-05 04:00:00"
    },
    "2008":{
        "id":2008,
        "OpenTime":"2021-01-14 04:00:00",
        "CloseTime":"2021-08-12 04:00:00"
    },
    "2009":{
        "id":2009,
        "OpenTime":"2021-01-14 04:00:00",
        "CloseTime":"2021-08-12 04:00:00"
    },
    "2010":{
        "id":2010,
        "OpenTime":"2021-01-14 04:00:00",
        "CloseTime":"2021-08-12 04:00:00"
    },
    "2011":{
        "id":2011,
        "OpenTime":"2021-01-14 04:00:00",
        "CloseTime":"2021-08-19 04:00:00"
    },
    "2012":{
        "id":2012,
        "OpenTime":"2021-01-14 04:00:00",
        "CloseTime":"2021-08-19 04:00:00"
    },
    "2013":{
        "id":2013,
        "OpenTime":"2021-01-14 04:00:00",
        "CloseTime":"2021-08-19 04:00:00"
    },
    "2014":{
        "id":2014,
        "OpenTime":"2021-01-14 04:00:00",
        "CloseTime":"2021-08-19 04:00:00"
    },
    "2015":{
        "id":2015,
        "OpenTime":"2021-01-14 04:00:00",
        "CloseTime":"2021-08-19 04:00:00"
    },
    "2016":{
        "id":2016,
        "OpenTime":"2021-01-14 04:00:00",
        "CloseTime":"2021-09-02 04:00:00"
    },
    "2017":{
        "id":2017,
        "OpenTime":"2021-01-14 04:00:00",
        "CloseTime":"2021-09-02 04:00:00"
    },
    "2018":{
        "id":2018,
        "OpenTime":"2021-01-14 04:00:00",
        "CloseTime":"2021-09-02 04:00:00"
    },
    "2019":{
        "id":2019,
        "OpenTime":"2021-01-14 04:00:00",
        "CloseTime":"2021-09-02 04:00:00"
    },
    "2020":{
        "id":2020,
        "OpenTime":"2021-01-14 04:00:00",
        "CloseTime":"2021-09-16 04:00:00"
    },
    "2021":{
        "id":2021,
        "OpenTime":"2021-01-14 04:00:00",
        "CloseTime":"2021-09-16 04:00:00"
    },
    "2022":{
        "id":2022,
        "OpenTime":"2021-01-14 04:00:00",
        "CloseTime":"2021-09-16 04:00:00"
    },
    "2023":{
        "id":2023,
        "OpenTime":"2021-01-14 04:00:00",
        "CloseTime":"2021-09-16 04:00:00"
    },
    "2024":{
        "id":2024,
        "OpenTime":"2021-01-14 04:00:00",
        "CloseTime":"2021-09-23 04:00:00"
    },
    "2025":{
        "id":2025,
        "OpenTime":"2021-01-14 04:00:00",
        "CloseTime":"2021-09-23 04:00:00"
    },
    "2026":{
        "id":2026,
        "OpenTime":"2021-01-14 04:00:00",
        "CloseTime":"2021-09-23 04:00:00"
    },
    "2027":{
        "id":2027,
        "OpenTime":"2021-01-14 04:00:00",
        "CloseTime":"2021-09-23 04:00:00"
    },
    "2028":{
        "id":2028,
        "OpenTime":"2021-01-14 04:00:00",
        "CloseTime":"2021-10-08 04:00:00"
    },
    "2029":{
        "id":2029,
        "OpenTime":"2021-01-14 04:00:00",
        "CloseTime":"2021-10-08 04:00:00"
    },
    "2030":{
        "id":2030,
        "OpenTime":"2021-01-14 04:00:00",
        "CloseTime":"2021-10-08 04:00:00"
    },
    "2031":{
        "id":2031,
        "OpenTime":"2021-01-14 04:00:00",
        "CloseTime":"2021-10-08 04:00:00"
    },
    "2032":{
        "id":2032,
        "OpenTime":"2021-01-14 04:00:00",
        "CloseTime":"2021-10-14 04:00:00"
    },
    "2033":{
        "id":2033,
        "OpenTime":"2021-01-14 04:00:00",
        "CloseTime":"2021-10-14 04:00:00"
    },
    "2034":{
        "id":2034,
        "OpenTime":"2021-01-14 04:00:00",
        "CloseTime":"2021-10-14 04:00:00"
    },
    "2035":{
        "id":2035,
        "OpenTime":"2021-01-14 04:00:00",
        "CloseTime":"2021-10-14 04:00:00"
    },
    "2036":{
        "id":2036,
        "OpenTime":"2021-01-14 04:00:00",
        "CloseTime":"2021-10-14 04:00:00"
    },
    "2037":{
        "id":2037,
        "OpenTime":"2021-01-14 04:00:00",
        "CloseTime":"2021-10-14 04:00:00"
    },
    "2038":{
        "id":2038,
        "OpenTime":"2021-01-14 04:00:00",
        "CloseTime":"2021-10-14 04:00:00"
    },
    "2039":{
        "id":2039,
        "OpenTime":"2021-01-14 04:00:00",
        "CloseTime":"2021-10-28 04:00:00"
    },
    "2040":{
        "id":2040,
        "OpenTime":"2021-01-14 04:00:00",
        "CloseTime":"2021-10-28 04:00:00"
    },
    "2041":{
        "id":2041,
        "OpenTime":"2021-01-14 04:00:00",
        "CloseTime":"2021-10-28 04:00:00"
    },
    "2042":{
        "id":2042,
        "OpenTime":"2021-01-14 04:00:00",
        "CloseTime":"2021-10-28 04:00:00"
    },
    "2043":{
        "id":2043,
        "OpenTime":"2021-01-14 04:00:00",
        "CloseTime":"2021-10-28 04:00:00"
    },
    "2044":{
        "id":2044,
        "OpenTime":"2021-01-14 04:00:00",
        "CloseTime":"2021-10-21 04:00:00"
    },
    "2045":{
        "id":2045,
        "OpenTime":"2021-01-14 04:00:00",
        "CloseTime":"2021-10-21 04:00:00"
    },
    "2046":{
        "id":2046,
        "OpenTime":"2021-01-14 04:00:00",
        "CloseTime":"2021-10-21 04:00:00"
    },
    "2047":{
        "id":2047,
        "OpenTime":"2021-01-14 04:00:00",
        "CloseTime":"2021-10-21 04:00:00"
    },
    "2048":{
        "id":2048,
        "OpenTime":"2021-01-14 04:00:00",
        "CloseTime":"2021-11-04 04:00:00"
    },
    "2049":{
        "id":2049,
        "OpenTime":"2021-01-14 04:00:00",
        "CloseTime":"2021-11-04 04:00:00"
    },
    "2050":{
        "id":2050,
        "OpenTime":"2021-01-14 04:00:00",
        "CloseTime":"2021-11-04 04:00:00"
    },
    "2051":{
        "id":2051,
        "OpenTime":"2021-01-14 04:00:00",
        "CloseTime":"2021-11-04 04:00:00"
    },
    "2052":{
        "id":2052,
        "OpenTime":"2021-01-14 04:00:00",
        "CloseTime":"2021-11-11 04:00:00"
    },
    "2053":{
        "id":2053,
        "OpenTime":"2021-01-14 04:00:00",
        "CloseTime":"2021-11-11 04:00:00"
    },
    "2054":{
        "id":2054,
        "OpenTime":"2021-01-14 04:00:00",
        "CloseTime":"2021-11-11 04:00:00"
    },
    "2055":{
        "id":2055,
        "OpenTime":"2021-01-14 04:00:00",
        "CloseTime":"2021-11-11 04:00:00"
    },
    "2056":{
        "id":2056,
        "OpenTime":"2021-01-14 04:00:00",
        "CloseTime":"2021-11-18 04:00:00"
    },
    "2057":{
        "id":2057,
        "OpenTime":"2021-01-14 04:00:00",
        "CloseTime":"2021-11-18 04:00:00"
    },
    "2058":{
        "id":2058,
        "OpenTime":"2021-01-14 04:00:00",
        "CloseTime":"2021-11-18 04:00:00"
    },
    "2059":{
        "id":2059,
        "OpenTime":"2021-01-14 04:00:00",
        "CloseTime":"2021-11-18 04:00:00"
    },
    "2060":{
        "id":2060,
        "OpenTime":"2021-01-14 04:00:00",
        "CloseTime":"2021-11-18 04:00:00"
    },
    "2061":{
        "id":2061,
        "OpenTime":"2021-01-14 04:00:00",
        "CloseTime":"2021-11-18 04:00:00"
    },
    "2062":{
        "id":2062,
        "OpenTime":"2021-01-14 04:00:00",
        "CloseTime":"2021-11-25 04:00:00"
    },
    "2063":{
        "id":2063,
        "OpenTime":"2021-01-14 04:00:00",
        "CloseTime":"2021-11-25 04:00:00"
    },
    "2064":{
        "id":2064,
        "OpenTime":"2021-01-14 04:00:00",
        "CloseTime":"2021-11-25 04:00:00"
    },
    "2065":{
        "id":2065,
        "OpenTime":"2021-01-14 04:00:00",
        "CloseTime":"2021-11-25 04:00:00"
    },
    "2066":{
        "id":2066,
        "OpenTime":"2021-01-14 04:00:00",
        "CloseTime":"2021-12-02 04:00:00"
    },
    "2067":{
        "id":2067,
        "OpenTime":"2021-01-14 04:00:00",
        "CloseTime":"2021-12-02 04:00:00"
    },
    "2068":{
        "id":2068,
        "OpenTime":"2021-01-14 04:00:00",
        "CloseTime":"2021-12-02 04:00:00"
    },
    "2069":{
        "id":2069,
        "OpenTime":"2021-01-14 04:00:00",
        "CloseTime":"2021-12-02 04:00:00"
    },
    "2070":{
        "id":2070,
        "OpenTime":"2021-01-14 04:00:00",
        "CloseTime":"2021-12-02 04:00:00"
    },
    "2071":{
        "id":2071,
        "OpenTime":"2021-01-14 04:00:00",
        "CloseTime":"2021-12-09 04:00:00"
    },
    "2072":{
        "id":2072,
        "OpenTime":"2021-01-14 04:00:00",
        "CloseTime":"2021-12-09 04:00:00"
    },
    "2073":{
        "id":2073,
        "OpenTime":"2021-01-14 04:00:00",
        "CloseTime":"2021-12-09 04:00:00"
    },
    "2074":{
        "id":2074,
        "OpenTime":"2021-01-14 04:00:00",
        "CloseTime":"2021-12-09 04:00:00"
    },
    "2075":{
        "id":2075,
        "OpenTime":"2021-01-14 04:00:00",
        "CloseTime":"2021-12-16 04:00:00"
    },
    "2076":{
        "id":2076,
        "OpenTime":"2021-01-14 04:00:00",
        "CloseTime":"2021-12-16 04:00:00"
    },
    "2077":{
        "id":2077,
        "OpenTime":"2021-01-14 04:00:00",
        "CloseTime":"2021-12-16 04:00:00"
    },
    "2078":{
        "id":2078,
        "OpenTime":"2021-01-14 04:00:00",
        "CloseTime":"2021-12-16 04:00:00"
    },
    "2079":{
        "id":2079,
        "OpenTime":"2021-01-14 04:00:00",
        "CloseTime":"2021-12-23 04:00:00"
    },
    "2080":{
        "id":2080,
        "OpenTime":"2021-01-14 04:00:00",
        "CloseTime":"2021-12-23 04:00:00"
    },
    "2081":{
        "id":2081,
        "OpenTime":"2021-01-14 04:00:00",
        "CloseTime":"2021-12-23 04:00:00"
    },
    "2082":{
        "id":2082,
        "OpenTime":"2021-01-14 04:00:00",
        "CloseTime":"2021-12-23 04:00:00"
    },
    "2083":{
        "id":2083,
        "OpenTime":"2021-12-23 04:00:00",
        "CloseTime":"2022-01-06 03:59:59"
    },
    "2084":{
        "id":2084,
        "OpenTime":"2021-12-23 04:00:00",
        "CloseTime":"2022-01-06 03:59:59"
    },
    "2085":{
        "id":2085,
        "OpenTime":"2021-12-23 04:00:00",
        "CloseTime":"2022-01-06 03:59:59"
    },
    "2086":{
        "id":2086,
        "OpenTime":"2021-12-23 04:00:00",
        "CloseTime":"2022-01-06 03:59:59"
    },
    "2087":{
        "id":2087,
        "OpenTime":"2021-12-23 04:00:00",
        "CloseTime":"2022-01-06 03:59:59"
    },
    "2088":{
        "id":2088,
        "OpenTime":"2021-01-14 04:00:00",
        "CloseTime":"2022-01-06 03:59:59"
    },
    "2089":{
        "id":2089,
        "OpenTime":"2021-01-14 04:00:00",
        "CloseTime":"2022-01-06 03:59:59"
    },
    "2090":{
        "id":2090,
        "OpenTime":"2021-01-14 04:00:00",
        "CloseTime":"2022-01-06 03:59:59"
    },
    "2091":{
        "id":2091,
        "OpenTime":"2021-01-14 04:00:00",
        "CloseTime":"2022-01-06 03:59:59"
    },
    "2092":{
        "id":2092,
        "OpenTime":"2021-01-14 04:00:00",
        "CloseTime":"2022-01-13 03:59:59"
    },
    "2093":{
        "id":2093,
        "OpenTime":"2021-01-14 04:00:00",
        "CloseTime":"2022-01-13 03:59:59"
    },
    "2094":{
        "id":2094,
        "OpenTime":"2021-01-14 04:00:00",
        "CloseTime":"2022-01-13 03:59:59"
    },
    "2095":{
        "id":2095,
        "OpenTime":"2021-01-14 04:00:00",
        "CloseTime":"2022-01-13 03:59:59"
    },
    "2096":{
        "id":2096,
        "OpenTime":"2022-01-20 04:00:00",
        "CloseTime":"2022-01-21 03:59:59"
    },
    "2097":{
        "id":2097,
        "OpenTime":"2022-01-21 04:00:00",
        "CloseTime":"2022-01-22 03:59:59"
    },
    "2098":{
        "id":2098,
        "OpenTime":"2022-01-22 04:00:00",
        "CloseTime":"2022-01-23 03:59:59"
    },
    "2099":{
        "id":2099,
        "OpenTime":"2022-01-23 04:00:00",
        "CloseTime":"2022-01-24 03:59:59"
    },
    "2100":{
        "id":2100,
        "OpenTime":"2022-01-24 04:00:00",
        "CloseTime":"2022-01-25 03:59:59"
    },
    "2101":{
        "id":2101,
        "OpenTime":"2022-01-25 04:00:00",
        "CloseTime":"2022-01-26 03:59:59"
    },
    "2102":{
        "id":2102,
        "OpenTime":"2022-01-26 04:00:00",
        "CloseTime":"2022-01-27 03:59:59"
    },
    "2103":{
        "id":2103,
        "OpenTime":"2022-01-27 04:00:00",
        "CloseTime":"2022-01-28 03:59:59"
    },
    "2104":{
        "id":2104,
        "OpenTime":"2022-01-28 04:00:00",
        "CloseTime":"2022-01-29 03:59:59"
    },
    "2105":{
        "id":2105,
        "OpenTime":"2022-01-29 04:00:00",
        "CloseTime":"2022-01-30 03:59:59"
    },
    "2106":{
        "id":2106,
        "OpenTime":"2022-01-30 04:00:00",
        "CloseTime":"2022-01-31 03:59:59"
    },
    "2107":{
        "id":2107,
        "OpenTime":"2022-01-31 04:00:00",
        "CloseTime":"2022-02-01 03:59:59"
    },
    "2108":{
        "id":2108,
        "OpenTime":"2022-02-01 04:00:00",
        "CloseTime":"2022-02-02 03:59:59"
    },
    "2109":{
        "id":2109,
        "OpenTime":"2022-02-02 04:00:00",
        "CloseTime":"2022-02-03 03:59:59"
    },
    "2110":{
        "id":2110,
        "OpenTime":"2022-02-03 04:00:00",
        "CloseTime":"2022-02-04 03:59:59"
    },
    "2111":{
        "id":2111,
        "OpenTime":"2022-02-04 04:00:00",
        "CloseTime":"2022-02-05 03:59:59"
    },
    "2112":{
        "id":2112,
        "OpenTime":"2022-02-05 04:00:00",
        "CloseTime":"2022-02-06 03:59:59"
    },
    "2113":{
        "id":2113,
        "OpenTime":"2022-02-06 04:00:00",
        "CloseTime":"2022-02-07 03:59:59"
    },
    "2114":{
        "id":2114,
        "OpenTime":"2022-02-07 04:00:00",
        "CloseTime":"2022-02-08 03:59:59"
    },
    "2115":{
        "id":2115,
        "OpenTime":"2022-02-08 04:00:00",
        "CloseTime":"2022-02-09 03:59:59"
    },
    "2116":{
        "id":2116,
        "OpenTime":"2022-02-09 04:00:00",
        "CloseTime":"2022-02-10 03:59:59"
    },
    "2117":{
        "id":2117,
        "OpenTime":"2022-01-20 04:00:00",
        "CloseTime":"2022-01-27 03:59:59"
    },
    "2118":{
        "id":2118,
        "OpenTime":"2022-01-20 04:00:00",
        "CloseTime":"2022-01-27 03:59:59"
    },
    "2119":{
        "id":2119,
        "OpenTime":"2022-01-20 04:00:00",
        "CloseTime":"2022-01-27 03:59:59"
    },
    "2120":{
        "id":2120,
        "OpenTime":"2022-01-20 04:00:00",
        "CloseTime":"2022-01-27 03:59:59"
    },
    "2121":{
        "id":2121,
        "OpenTime":"2021-01-14 04:00:00",
        "CloseTime":"2022-01-20 03:59:59"
    },
    "2122":{
        "id":2122,
        "OpenTime":"2021-01-14 04:00:00",
        "CloseTime":"2022-01-20 03:59:59"
    },
    "2123":{
        "id":2123,
        "OpenTime":"2021-01-14 04:00:00",
        "CloseTime":"2022-01-20 03:59:59"
    },
    "2124":{
        "id":2124,
        "OpenTime":"2021-01-14 04:00:00",
        "CloseTime":"2022-01-20 03:59:59"
    },
    "2125":{
        "id":2125,
        "OpenTime":"2022-01-27 04:00:00",
        "CloseTime":"2022-02-03 03:59:59"
    },
    "2126":{
        "id":2126,
        "OpenTime":"2022-01-27 04:00:00",
        "CloseTime":"2022-02-03 03:59:59"
    },
    "2127":{
        "id":2127,
        "OpenTime":"2022-01-27 04:00:00",
        "CloseTime":"2022-02-03 03:59:59"
    },
    "2128":{
        "id":2128,
        "OpenTime":"2022-01-27 04:00:00",
        "CloseTime":"2022-02-03 03:59:59"
    },
    "2129":{
        "id":2129,
        "OpenTime":"2022-02-03 04:00:00",
        "CloseTime":"2022-02-10 03:59:59"
    },
    "2130":{
        "id":2130,
        "OpenTime":"2022-02-03 04:00:00",
        "CloseTime":"2022-02-10 03:59:59"
    },
    "2131":{
        "id":2131,
        "OpenTime":"2022-02-03 04:00:00",
        "CloseTime":"2022-02-10 03:59:59"
    },
    "2132":{
        "id":2132,
        "OpenTime":"2022-02-03 04:00:00",
        "CloseTime":"2022-02-10 03:59:59"
    },
    "2133":{
        "id":2133,
        "OpenTime":"2022-02-10 04:00:00",
        "CloseTime":"2022-02-24 03:59:59"
    },
    "2134":{
        "id":2134,
        "OpenTime":"2022-02-10 04:00:00",
        "CloseTime":"2022-02-24 03:59:59"
    },
    "2135":{
        "id":2135,
        "OpenTime":"2022-02-10 04:00:00",
        "CloseTime":"2022-02-24 03:59:59"
    },
    "2136":{
        "id":2136,
        "OpenTime":"2022-02-10 04:00:00",
        "CloseTime":"2022-02-24 03:59:59"
    },
    "2137":{
        "id":2137,
        "OpenTime":"2022-02-10 04:00:00",
        "CloseTime":"2022-02-24 03:59:59"
    },
    "2138":{
        "id":2138,
        "OpenTime":"2022-02-17 04:00:00",
        "CloseTime":"2022-03-03 03:59:59"
    },
    "2139":{
        "id":2139,
        "OpenTime":"2022-02-17 04:00:00",
        "CloseTime":"2022-03-03 03:59:59"
    },
    "2140":{
        "id":2140,
        "OpenTime":"2022-02-17 04:00:00",
        "CloseTime":"2022-03-03 03:59:59"
    },
    "2141":{
        "id":2141,
        "OpenTime":"2022-02-17 04:00:00",
        "CloseTime":"2022-03-03 03:59:59"
    },
    "2142":{
        "id":2142,
        "OpenTime":"2022-03-10 04:00:00",
        "CloseTime":"2022-03-17 03:59:59"
    },
    "2143":{
        "id":2143,
        "OpenTime":"2022-03-10 04:00:00",
        "CloseTime":"2022-03-17 03:59:59"
    },
    "2144":{
        "id":2144,
        "OpenTime":"2022-03-10 04:00:00",
        "CloseTime":"2022-03-17 03:59:59"
    },
    "2145":{
        "id":2145,
        "OpenTime":"2022-03-10 04:00:00",
        "CloseTime":"2022-03-17 03:59:59"
    },
    "2146":{
        "id":2146,
        "OpenTime":"2022-03-17 04:00:00",
        "CloseTime":"2022-03-24 03:59:59"
    },
    "2147":{
        "id":2147,
        "OpenTime":"2022-03-17 04:00:00",
        "CloseTime":"2022-03-24 03:59:59"
    },
    "2148":{
        "id":2148,
        "OpenTime":"2022-03-17 04:00:00",
        "CloseTime":"2022-03-24 03:59:59"
    },
    "2149":{
        "id":2149,
        "OpenTime":"2022-03-17 04:00:00",
        "CloseTime":"2022-03-24 03:59:59"
    },
    "2150":{
        "id":2150,
        "OpenTime":"2022-03-03 04:00:00",
        "CloseTime":"2022-03-10 03:59:59"
    },
    "2151":{
        "id":2151,
        "OpenTime":"2022-03-03 04:00:00",
        "CloseTime":"2022-03-10 03:59:59"
    },
    "2152":{
        "id":2152,
        "OpenTime":"2022-03-03 04:00:00",
        "CloseTime":"2022-03-10 03:59:59"
    },
    "2153":{
        "id":2153,
        "OpenTime":"2022-03-03 04:00:00",
        "CloseTime":"2022-03-10 03:59:59"
    },
    "2154":{
        "id":2154,
        "OpenTime":"2022-03-31 04:00:00",
        "CloseTime":"2022-04-14 03:59:59"
    },
    "2155":{
        "id":2155,
        "OpenTime":"2022-03-31 04:00:00",
        "CloseTime":"2022-04-14 03:59:59"
    },
    "2156":{
        "id":2156,
        "OpenTime":"2022-03-31 04:00:00",
        "CloseTime":"2022-04-14 03:59:59"
    },
    "2157":{
        "id":2157,
        "OpenTime":"2022-03-31 04:00:00",
        "CloseTime":"2022-04-14 03:59:59"
    },
    "2158":{
        "id":2158,
        "OpenTime":"2022-03-31 04:00:00",
        "CloseTime":"2022-04-14 03:59:59"
    },
    "2159":{
        "id":2159,
        "OpenTime":"2022-04-21 04:00:00",
        "CloseTime":"2022-05-05 03:59:59"
    },
    "2160":{
        "id":2160,
        "OpenTime":"2022-04-21 04:00:00",
        "CloseTime":"2022-05-05 03:59:59"
    },
    "2161":{
        "id":2161,
        "OpenTime":"2022-04-21 04:00:00",
        "CloseTime":"2022-05-05 03:59:59"
    },
    "2162":{
        "id":2162,
        "OpenTime":"2022-04-21 04:00:00",
        "CloseTime":"2022-05-05 03:59:59"
    },
    "2167":{
        "id":2167,
        "OpenTime":"2022-05-13 04:00:00",
        "CloseTime":"2022-05-26 03:59:59"
    },
    "2168":{
        "id":2168,
        "OpenTime":"2022-05-13 04:00:00",
        "CloseTime":"2022-05-26 03:59:59"
    },
    "2169":{
        "id":2169,
        "OpenTime":"2022-05-13 04:00:00",
        "CloseTime":"2022-05-26 03:59:59"
    },
    "2170":{
        "id":2170,
        "OpenTime":"2022-05-13 04:00:00",
        "CloseTime":"2022-05-26 03:59:59"
    },
    "2175":{
        "id":2175,
        "OpenTime":"2022-05-26 04:00:00",
        "CloseTime":"2022-06-09 03:59:59"
    },
    "2176":{
        "id":2176,
        "OpenTime":"2022-05-26 04:00:00",
        "CloseTime":"2022-06-09 03:59:59"
    },
    "2177":{
        "id":2177,
        "OpenTime":"2022-05-26 04:00:00",
        "CloseTime":"2022-06-09 03:59:59"
    },
    "2178":{
        "id":2178,
        "OpenTime":"2022-05-26 04:00:00",
        "CloseTime":"2022-06-09 03:59:59"
    },
    "2179":{
        "id":2179,
        "OpenTime":"2022-05-26 04:00:00",
        "CloseTime":"2022-06-09 03:59:59"
    },
    "2180":{
        "id":2180,
        "OpenTime":"2022-06-16 04:00:00",
        "CloseTime":"2022-06-23 03:59:59"
    },
    "2181":{
        "id":2181,
        "OpenTime":"2022-06-16 04:00:00",
        "CloseTime":"2022-06-23 03:59:59"
    },
    "2182":{
        "id":2182,
        "OpenTime":"2022-06-16 04:00:00",
        "CloseTime":"2022-06-23 03:59:59"
    },
    "2183":{
        "id":2183,
        "OpenTime":"2022-06-16 04:00:00",
        "CloseTime":"2022-06-23 03:59:59"
    },
    "2184":{
        "id":2184,
        "OpenTime":"2022-06-16 04:00:00",
        "CloseTime":"2022-06-23 03:59:59"
    },
    "2185":{
        "id":2185,
        "OpenTime":"2022-06-16 04:00:00",
        "CloseTime":"2022-06-23 03:59:59"
    },
    "2186":{
        "id":2186,
        "OpenTime":"2022-06-16 04:00:00",
        "CloseTime":"2022-06-23 03:59:59"
    },
    "2187":{
        "id":2187,
        "OpenTime":"2022-06-23 04:00:00",
        "CloseTime":"2022-06-30 03:59:59"
    },
    "2188":{
        "id":2188,
        "OpenTime":"2022-06-23 04:00:00",
        "CloseTime":"2022-06-30 03:59:59"
    },
    "2189":{
        "id":2189,
        "OpenTime":"2022-06-23 04:00:00",
        "CloseTime":"2022-06-30 03:59:59"
    },
    "2190":{
        "id":2190,
        "OpenTime":"2022-06-23 04:00:00",
        "CloseTime":"2022-06-30 03:59:59"
    },
    "2191":{
        "id":2191,
        "OpenTime":"2022-06-23 04:00:00",
        "CloseTime":"2022-06-30 03:59:59"
    },
    "2192":{
        "id":2192,
        "OpenTime":"2022-06-23 04:00:00",
        "CloseTime":"2022-06-30 03:59:59"
    },
    "2193":{
        "id":2193,
        "OpenTime":"2022-06-23 04:00:00",
        "CloseTime":"2022-06-30 03:59:59"
    },
    "2194":{
        "id":2194,
        "OpenTime":"2022-06-23 04:00:00",
        "CloseTime":"2022-07-14 03:59:59"
    },
    "2195":{
        "id":2195,
        "OpenTime":"2022-06-23 04:00:00",
        "CloseTime":"2022-07-14 03:59:59"
    },
    "2196":{
        "id":2196,
        "OpenTime":"2022-06-23 04:00:00",
        "CloseTime":"2022-07-14 03:59:59"
    },
    "2197":{
        "id":2197,
        "OpenTime":"2022-06-23 04:00:00",
        "CloseTime":"2022-07-14 03:59:59"
    },
    "2198":{
        "id":2198,
        "OpenTime":"2022-07-28 04:00:00",
        "CloseTime":"2022-08-11 03:59:59"
    },
    "2199":{
        "id":2199,
        "OpenTime":"2022-07-28 04:00:00",
        "CloseTime":"2022-08-11 03:59:59"
    },
    "2200":{
        "id":2200,
        "OpenTime":"2022-07-28 04:00:00",
        "CloseTime":"2022-08-11 03:59:59"
    },
    "2201":{
        "id":2201,
        "OpenTime":"2022-07-28 04:00:00",
        "CloseTime":"2022-08-11 03:59:59"
    },
    "2202":{
        "id":2202,
        "OpenTime":"2022-08-18 04:00:00",
        "CloseTime":"2022-09-01 03:59:59"
    },
    "2203":{
        "id":2203,
        "OpenTime":"2022-08-18 04:00:00",
        "CloseTime":"2022-09-01 03:59:59"
    },
    "2204":{
        "id":2204,
        "OpenTime":"2022-08-18 04:00:00",
        "CloseTime":"2022-09-01 03:59:59"
    },
    "2205":{
        "id":2205,
        "OpenTime":"2022-08-18 04:00:00",
        "CloseTime":"2022-09-01 03:59:59"
    },
    "2206":{
        "id":2206,
        "OpenTime":"2022-09-08 04:00:00",
        "CloseTime":"2022-09-22 03:59:59"
    },
    "2207":{
        "id":2207,
        "OpenTime":"2022-09-08 04:00:00",
        "CloseTime":"2022-09-22 03:59:59"
    },
    "2208":{
        "id":2208,
        "OpenTime":"2022-09-08 04:00:00",
        "CloseTime":"2022-09-22 03:59:59"
    },
    "2209":{
        "id":2209,
        "OpenTime":"2022-09-08 04:00:00",
        "CloseTime":"2022-09-22 03:59:59"
    },
    "2210":{
        "id":2210,
        "OpenTime":"2022-09-27 04:00:00",
        "CloseTime":"2022-11-10 03:59:59"
    },
    "2211":{
        "id":2211,
        "OpenTime":"2022-09-27 04:00:00",
        "CloseTime":"2022-11-10 03:59:59"
    },
    "2212":{
        "id":2212,
        "OpenTime":"2022-09-27 04:00:00",
        "CloseTime":"2022-11-10 03:59:59"
    },
    "2213":{
        "id":2213,
        "OpenTime":"2022-09-27 04:00:00",
        "CloseTime":"2022-11-10 03:59:59"
    },
    "2214":{
        "id":2214,
        "OpenTime":"2022-09-23 04:00:00",
        "CloseTime":"2022-10-13 03:59:59"
    },
    "2215":{
        "id":2215,
        "OpenTime":"2022-09-23 04:00:00",
        "CloseTime":"2022-10-13 03:59:59"
    },
    "2216":{
        "id":2216,
        "OpenTime":"2022-09-23 04:00:00",
        "CloseTime":"2022-10-13 03:59:59"
    },
    "2217":{
        "id":2217,
        "OpenTime":"2022-09-23 04:00:00",
        "CloseTime":"2022-10-13 03:59:59"
    },
    "2218":{
        "id":2218,
        "OpenTime":"2022-10-11 04:00:00",
        "CloseTime":"2022-10-18 03:59:59"
    },
    "2219":{
        "id":2219,
        "OpenTime":"2022-10-11 04:00:00",
        "CloseTime":"2022-10-18 03:59:59"
    },
    "2220":{
        "id":2220,
        "OpenTime":"2022-10-11 04:00:00",
        "CloseTime":"2022-10-18 03:59:59"
    },
    "2221":{
        "id":2221,
        "OpenTime":"2022-10-11 04:00:00",
        "CloseTime":"2022-10-18 03:59:59"
    },
    "2222":{
        "id":2222,
        "OpenTime":"2022-10-18 04:00:00",
        "CloseTime":"2022-10-25 03:59:59"
    },
    "2223":{
        "id":2223,
        "OpenTime":"2022-10-18 04:00:00",
        "CloseTime":"2022-10-25 03:59:59"
    },
    "2224":{
        "id":2224,
        "OpenTime":"2022-10-18 04:00:00",
        "CloseTime":"2022-10-25 03:59:59"
    },
    "2225":{
        "id":2225,
        "OpenTime":"2022-10-18 04:00:00",
        "CloseTime":"2022-10-25 03:59:59"
    },
    "2226":{
        "id":2226,
        "OpenTime":"2022-10-25 04:00:00",
        "CloseTime":"2022-10-31 03:59:59"
    },
    "2227":{
        "id":2227,
        "OpenTime":"2022-10-25 04:00:00",
        "CloseTime":"2022-10-31 03:59:59"
    },
    "2228":{
        "id":2228,
        "OpenTime":"2022-10-25 04:00:00",
        "CloseTime":"2022-10-31 03:59:59"
    },
    "2229":{
        "id":2229,
        "OpenTime":"2022-10-25 04:00:00",
        "CloseTime":"2022-10-31 03:59:59"
    },
    "2230":{
        "id":2230,
        "OpenTime":"2022-09-23 04:00:00",
        "CloseTime":"2022-10-13 03:59:59"
    },
    "2231":{
        "id":2231,
        "OpenTime":"2022-09-23 04:00:00",
        "CloseTime":"2022-10-13 03:59:59"
    },
    "2232":{
        "id":2232,
        "OpenTime":"2022-09-23 04:00:00",
        "CloseTime":"2022-10-13 03:59:59"
    },
    "2233":{
        "id":2233,
        "OpenTime":"2022-09-23 04:00:00",
        "CloseTime":"2022-10-13 03:59:59"
    },
    "2238":{
        "id":2238,
        "OpenTime":"2022-10-15 04:00:00",
        "CloseTime":"2022-11-17 03:59:59"
    },
    "2239":{
        "id":2239,
        "OpenTime":"2022-10-15 04:00:00",
        "CloseTime":"2022-11-17 03:59:59"
    },
    "2240":{
        "id":2240,
        "OpenTime":"2022-10-15 04:00:00",
        "CloseTime":"2022-11-17 03:59:59"
    },
    "2241":{
        "id":2241,
        "OpenTime":"2022-10-15 04:00:00",
        "CloseTime":"2022-11-17 03:59:59"
    },
    "2242":{
        "id":2242,
        "OpenTime":"2022-11-17 04:00:00",
        "CloseTime":"2022-11-24 03:59:59"
    },
    "2243":{
        "id":2243,
        "OpenTime":"2022-11-17 04:00:00",
        "CloseTime":"2022-11-24 03:59:59"
    },
    "2244":{
        "id":2244,
        "OpenTime":"2022-11-17 04:00:00",
        "CloseTime":"2022-11-24 03:59:59"
    },
    "2245":{
        "id":2245,
        "OpenTime":"2022-11-17 04:00:00",
        "CloseTime":"2022-11-24 03:59:59"
    },
    "2246":{
        "id":2246,
        "OpenTime":"2022-11-24 04:00:00",
        "CloseTime":"2022-12-01 03:59:59"
    },
    "2247":{
        "id":2247,
        "OpenTime":"2022-11-24 04:00:00",
        "CloseTime":"2022-12-01 03:59:59"
    },
    "2248":{
        "id":2248,
        "OpenTime":"2022-11-24 04:00:00",
        "CloseTime":"2022-12-01 03:59:59"
    },
    "2249":{
        "id":2249,
        "OpenTime":"2022-11-24 04:00:00",
        "CloseTime":"2022-12-01 03:59:59"
    },
    "2250":{
        "id":2250,
        "OpenTime":"2022-12-01 04:00:00",
        "CloseTime":"2022-12-08 03:59:59"
    },
    "2251":{
        "id":2251,
        "OpenTime":"2022-12-01 04:00:00",
        "CloseTime":"2022-12-08 03:59:59"
    },
    "2252":{
        "id":2252,
        "OpenTime":"2022-12-01 04:00:00",
        "CloseTime":"2022-12-08 03:59:59"
    },
    "2253":{
        "id":2253,
        "OpenTime":"2022-12-01 04:00:00",
        "CloseTime":"2022-12-08 03:59:59"
    },
    "2254":{
        "id":2254,
        "OpenTime":"2022-12-08 04:00:00",
        "CloseTime":"2022-12-15 03:59:59"
    },
    "2255":{
        "id":2255,
        "OpenTime":"2022-12-08 04:00:00",
        "CloseTime":"2022-12-15 03:59:59"
    },
    "2256":{
        "id":2256,
        "OpenTime":"2022-12-08 04:00:00",
        "CloseTime":"2022-12-15 03:59:59"
    },
    "2257":{
        "id":2257,
        "OpenTime":"2022-12-08 04:00:00",
        "CloseTime":"2022-12-15 03:59:59"
    },
    "2258":{
        "id":2258,
        "OpenTime":"2022-12-15 04:00:00",
        "CloseTime":"2022-12-22 03:59:59"
    },
    "2259":{
        "id":2259,
        "OpenTime":"2022-12-15 04:00:00",
        "CloseTime":"2022-12-22 03:59:59"
    },
    "2260":{
        "id":2260,
        "OpenTime":"2022-12-15 04:00:00",
        "CloseTime":"2022-12-22 03:59:59"
    },
    "2261":{
        "id":2261,
        "OpenTime":"2022-12-15 04:00:00",
        "CloseTime":"2022-12-22 03:59:59"
    },
    "2262":{
        "id":2262,
        "OpenTime":"2022-12-22 04:00:00",
        "CloseTime":"2022-12-29 03:59:59"
    },
    "2263":{
        "id":2263,
        "OpenTime":"2022-12-22 04:00:00",
        "CloseTime":"2022-12-29 03:59:59"
    },
    "2264":{
        "id":2264,
        "OpenTime":"2022-12-22 04:00:00",
        "CloseTime":"2022-12-29 03:59:59"
    },
    "2265":{
        "id":2265,
        "OpenTime":"2022-12-22 04:00:00",
        "CloseTime":"2022-12-29 03:59:59"
    },
    "2266":{
        "id":2266,
        "OpenTime":"2023-01-05 04:00:00",
        "CloseTime":"2023-01-12 03:59:59"
    },
    "2267":{
        "id":2267,
        "OpenTime":"2023-01-05 04:00:00",
        "CloseTime":"2023-01-12 03:59:59"
    },
    "2268":{
        "id":2268,
        "OpenTime":"2023-01-05 04:00:00",
        "CloseTime":"2023-01-12 03:59:59"
    },
    "2269":{
        "id":2269,
        "OpenTime":"2023-01-05 04:00:00",
        "CloseTime":"2023-01-12 03:59:59"
    },
    "2270":{
        "id":2270,
        "OpenTime":"2023-01-12 04:00:00",
        "CloseTime":"2023-01-19 03:59:59"
    },
    "2271":{
        "id":2271,
        "OpenTime":"2023-01-12 04:00:00",
        "CloseTime":"2023-01-19 03:59:59"
    },
    "2272":{
        "id":2272,
        "OpenTime":"2023-01-12 04:00:00",
        "CloseTime":"2023-01-19 03:59:59"
    },
    "2273":{
        "id":2273,
        "OpenTime":"2023-01-12 04:00:00",
        "CloseTime":"2023-01-19 03:59:59"
    },
    "2274":{
        "id":2274,
        "OpenTime":"2023-01-19 04:00:00",
        "CloseTime":"2023-01-26 03:59:59"
    },
    "2275":{
        "id":2275,
        "OpenTime":"2023-01-19 04:00:00",
        "CloseTime":"2023-01-26 03:59:59"
    },
    "2276":{
        "id":2276,
        "OpenTime":"2023-01-19 04:00:00",
        "CloseTime":"2023-01-26 03:59:59"
    },
    "2277":{
        "id":2277,
        "OpenTime":"2023-01-19 04:00:00",
        "CloseTime":"2023-01-26 03:59:59"
    },
    "2278":{
        "id":2278,
        "OpenTime":"2023-01-26 04:00:00",
        "CloseTime":"2023-02-02 03:59:59"
    },
    "2279":{
        "id":2279,
        "OpenTime":"2023-01-26 04:00:00",
        "CloseTime":"2023-02-02 03:59:59"
    },
    "2280":{
        "id":2280,
        "OpenTime":"2023-01-26 04:00:00",
        "CloseTime":"2023-02-02 03:59:59"
    },
    "2281":{
        "id":2281,
        "OpenTime":"2023-01-26 04:00:00",
        "CloseTime":"2023-02-02 03:59:59"
    },
    "2282":{
        "id":2282,
        "OpenTime":"2023-02-02 04:00:00",
        "CloseTime":"2023-02-09 03:59:59"
    },
    "2283":{
        "id":2283,
        "OpenTime":"2023-02-02 04:00:00",
        "CloseTime":"2023-02-09 03:59:59"
    },
    "2284":{
        "id":2284,
        "OpenTime":"2023-02-02 04:00:00",
        "CloseTime":"2023-02-09 03:59:59"
    },
    "2285":{
        "id":2285,
        "OpenTime":"2023-02-02 04:00:00",
        "CloseTime":"2023-02-09 03:59:59"
    },
    "2286":{
        "id":2286,
        "OpenTime":"2023-02-09 04:00:00",
        "CloseTime":"2023-02-16 03:59:59"
    },
    "2287":{
        "id":2287,
        "OpenTime":"2023-02-09 04:00:00",
        "CloseTime":"2023-02-16 03:59:59"
    },
    "2288":{
        "id":2288,
        "OpenTime":"2023-02-09 04:00:00",
        "CloseTime":"2023-02-16 03:59:59"
    },
    "2289":{
        "id":2289,
        "OpenTime":"2023-02-09 04:00:00",
        "CloseTime":"2023-02-16 03:59:59"
    },
    "2290":{
        "id":2290,
        "OpenTime":"2023-02-16 04:00:00",
        "CloseTime":"2023-02-23 03:59:59"
    },
    "2291":{
        "id":2291,
        "OpenTime":"2023-02-16 04:00:00",
        "CloseTime":"2023-02-23 03:59:59"
    },
    "2292":{
        "id":2292,
        "OpenTime":"2023-02-16 04:00:00",
        "CloseTime":"2023-02-23 03:59:59"
    },
    "2293":{
        "id":2293,
        "OpenTime":"2023-02-16 04:00:00",
        "CloseTime":"2023-02-23 03:59:59"
    },
    "2294":{
        "id":2294,
        "OpenTime":"2023-02-23 04:00:00",
        "CloseTime":"2023-03-02 03:59:59"
    },
    "2295":{
        "id":2295,
        "OpenTime":"2023-02-23 04:00:00",
        "CloseTime":"2023-03-02 03:59:59"
    },
    "2296":{
        "id":2296,
        "OpenTime":"2023-02-23 04:00:00",
        "CloseTime":"2023-03-02 03:59:59"
    },
    "2297":{
        "id":2297,
        "OpenTime":"2023-02-23 04:00:00",
        "CloseTime":"2023-03-02 03:59:59"
    },
    "2298":{
        "id":2298,
        "OpenTime":"2023-03-02 04:00:00",
        "CloseTime":"2023-03-09 03:59:59"
    },
    "2299":{
        "id":2299,
        "OpenTime":"2023-03-02 04:00:00",
        "CloseTime":"2023-03-09 03:59:59"
    },
    "2300":{
        "id":2300,
        "OpenTime":"2023-03-02 04:00:00",
        "CloseTime":"2023-03-09 03:59:59"
    },
    "2301":{
        "id":2301,
        "OpenTime":"2023-03-02 04:00:00",
        "CloseTime":"2023-03-09 03:59:59"
    },
    "2302":{
        "id":2302,
        "OpenTime":"2023-03-09 04:00:00",
        "CloseTime":"2023-03-16 03:59:59"
    },
    "2303":{
        "id":2303,
        "OpenTime":"2023-03-09 04:00:00",
        "CloseTime":"2023-03-16 03:59:59"
    },
    "2304":{
        "id":2304,
        "OpenTime":"2023-03-09 04:00:00",
        "CloseTime":"2023-03-16 03:59:59"
    },
    "2305":{
        "id":2305,
        "OpenTime":"2023-03-09 04:00:00",
        "CloseTime":"2023-03-16 03:59:59"
    },
    "2306":{
        "id":2306,
        "OpenTime":"2023-03-16 04:00:00",
        "CloseTime":"2023-03-23 03:59:59"
    },
    "2307":{
        "id":2307,
        "OpenTime":"2023-03-16 04:00:00",
        "CloseTime":"2023-03-23 03:59:59"
    },
    "2308":{
        "id":2308,
        "OpenTime":"2023-03-16 04:00:00",
        "CloseTime":"2023-03-23 03:59:59"
    },
    "2309":{
        "id":2309,
        "OpenTime":"2023-03-16 04:00:00",
        "CloseTime":"2023-03-23 03:59:59"
    },
    "2310":{
        "id":2310,
        "OpenTime":"2023-03-23 04:00:00",
        "CloseTime":"2023-03-30 03:59:59"
    },
    "2311":{
        "id":2311,
        "OpenTime":"2023-03-23 04:00:00",
        "CloseTime":"2023-03-30 03:59:59"
    },
    "2312":{
        "id":2312,
        "OpenTime":"2023-03-23 04:00:00",
        "CloseTime":"2023-03-30 03:59:59"
    },
    "2313":{
        "id":2313,
        "OpenTime":"2023-03-23 04:00:00",
        "CloseTime":"2023-03-30 03:59:59"
    },
    "2314":{
        "id":2314,
        "OpenTime":"2023-03-30 04:00:00",
        "CloseTime":"2023-04-06 03:59:59"
    },
    "2315":{
        "id":2315,
        "OpenTime":"2023-03-30 04:00:00",
        "CloseTime":"2023-04-06 03:59:59"
    },
    "2316":{
        "id":2316,
        "OpenTime":"2023-03-30 04:00:00",
        "CloseTime":"2023-04-06 03:59:59"
    },
    "2317":{
        "id":2317,
        "OpenTime":"2023-03-30 04:00:00",
        "CloseTime":"2023-04-06 03:59:59"
    },
    "2318":{
        "id":2318,
        "OpenTime":"2023-04-06 04:00:00",
        "CloseTime":"2023-04-13 03:59:59"
    },
    "2319":{
        "id":2319,
        "OpenTime":"2023-04-06 04:00:00",
        "CloseTime":"2023-04-13 03:59:59"
    },
    "2320":{
        "id":2320,
        "OpenTime":"2023-04-06 04:00:00",
        "CloseTime":"2023-04-13 03:59:59"
    },
    "2321":{
        "id":2321,
        "OpenTime":"2023-04-06 04:00:00",
        "CloseTime":"2023-04-13 03:59:59"
    },
    "2322":{
        "id":2322,
        "OpenTime":"2023-04-13 04:00:00",
        "CloseTime":"2023-04-20 03:59:59"
    },
    "2323":{
        "id":2323,
        "OpenTime":"2023-04-13 04:00:00",
        "CloseTime":"2023-04-20 03:59:59"
    },
    "2324":{
        "id":2324,
        "OpenTime":"2023-04-13 04:00:00",
        "CloseTime":"2023-04-20 03:59:59"
    },
    "2325":{
        "id":2325,
        "OpenTime":"2023-04-13 04:00:00",
        "CloseTime":"2023-04-20 03:59:59"
    },
    "2326":{
        "id":2326,
        "OpenTime":"2023-04-20 04:00:00",
        "CloseTime":"2023-04-27 03:59:59"
    },
    "2327":{
        "id":2327,
        "OpenTime":"2023-04-20 04:00:00",
        "CloseTime":"2023-04-27 03:59:59"
    },
    "2328":{
        "id":2328,
        "OpenTime":"2023-04-20 04:00:00",
        "CloseTime":"2023-04-27 03:59:59"
    },
    "2329":{
        "id":2329,
        "OpenTime":"2023-04-20 04:00:00",
        "CloseTime":"2023-04-27 03:59:59"
    },
    "2330":{
        "id":2330,
        "OpenTime":"2023-04-27 04:00:00",
        "CloseTime":"2023-05-04 03:59:59"
    },
    "2331":{
        "id":2331,
        "OpenTime":"2023-04-27 04:00:00",
        "CloseTime":"2023-05-04 03:59:59"
    },
    "2332":{
        "id":2332,
        "OpenTime":"2023-04-27 04:00:00",
        "CloseTime":"2023-05-04 03:59:59"
    },
    "2333":{
        "id":2333,
        "OpenTime":"2023-04-27 04:00:00",
        "CloseTime":"2023-05-04 03:59:59"
    },
    "2334":{
        "id":2334,
        "OpenTime":"2023-05-04 04:00:00",
        "CloseTime":"2023-05-11 03:59:59"
    },
    "2335":{
        "id":2335,
        "OpenTime":"2023-05-04 04:00:00",
        "CloseTime":"2023-05-11 03:59:59"
    },
    "2336":{
        "id":2336,
        "OpenTime":"2023-05-04 04:00:00",
        "CloseTime":"2023-05-11 03:59:59"
    },
    "2337":{
        "id":2337,
        "OpenTime":"2023-05-04 04:00:00",
        "CloseTime":"2023-05-11 03:59:59"
    },
    "2338":{
        "id":2338,
        "OpenTime":"2023-05-11 04:00:00",
        "CloseTime":"2023-05-18 03:59:59"
    },
    "2339":{
        "id":2339,
        "OpenTime":"2023-05-11 04:00:00",
        "CloseTime":"2023-05-18 03:59:59"
    },
    "2340":{
        "id":2340,
        "OpenTime":"2023-05-11 04:00:00",
        "CloseTime":"2023-05-18 03:59:59"
    },
    "2341":{
        "id":2341,
        "OpenTime":"2023-05-11 04:00:00",
        "CloseTime":"2023-05-18 03:59:59"
    },
    "2342":{
        "id":2342,
        "OpenTime":"2023-05-18 04:00:00",
        "CloseTime":"2023-05-25 03:59:59"
    },
    "2343":{
        "id":2343,
        "OpenTime":"2023-05-18 04:00:00",
        "CloseTime":"2023-05-25 03:59:59"
    },
    "2344":{
        "id":2344,
        "OpenTime":"2023-05-18 04:00:00",
        "CloseTime":"2023-05-25 03:59:59"
    },
    "2345":{
        "id":2345,
        "OpenTime":"2023-05-18 04:00:00",
        "CloseTime":"2023-05-25 03:59:59"
    },
    "2346":{
        "id":2346,
        "OpenTime":"2023-05-25 04:00:00",
        "CloseTime":"2023-06-01 03:59:59"
    },
    "2347":{
        "id":2347,
        "OpenTime":"2023-05-25 04:00:00",
        "CloseTime":"2023-06-01 03:59:59"
    },
    "2348":{
        "id":2348,
        "OpenTime":"2023-05-25 04:00:00",
        "CloseTime":"2023-06-01 03:59:59"
    },
    "2349":{
        "id":2349,
        "OpenTime":"2023-05-25 04:00:00",
        "CloseTime":"2023-06-01 03:59:59"
    },
    "2350":{
        "id":2350,
        "OpenTime":"2023-06-01 04:00:00",
        "CloseTime":"2023-06-08 03:59:59"
    },
    "2351":{
        "id":2351,
        "OpenTime":"2023-06-01 04:00:00",
        "CloseTime":"2023-06-08 03:59:59"
    },
    "2352":{
        "id":2352,
        "OpenTime":"2023-06-01 04:00:00",
        "CloseTime":"2023-06-08 03:59:59"
    },
    "2353":{
        "id":2353,
        "OpenTime":"2023-06-01 04:00:00",
        "CloseTime":"2023-06-08 03:59:59"
    },
    "2354":{
        "id":2354,
        "OpenTime":"2023-06-08 04:00:00",
        "CloseTime":"2023-06-15 03:59:59"
    },
    "2355":{
        "id":2355,
        "OpenTime":"2023-06-08 04:00:00",
        "CloseTime":"2023-06-15 03:59:59"
    },
    "2356":{
        "id":2356,
        "OpenTime":"2023-06-08 04:00:00",
        "CloseTime":"2023-06-15 03:59:59"
    },
    "2357":{
        "id":2357,
        "OpenTime":"2023-06-08 04:00:00",
        "CloseTime":"2023-06-15 03:59:59"
    },
    "2358":{
        "id":2358,
        "OpenTime":"2023-06-15 04:00:00",
        "CloseTime":"2023-06-22 03:59:59"
    },
    "2359":{
        "id":2359,
        "OpenTime":"2023-06-15 04:00:00",
        "CloseTime":"2023-06-22 03:59:59"
    },
    "2360":{
        "id":2360,
        "OpenTime":"2023-06-15 04:00:00",
        "CloseTime":"2023-06-22 03:59:59"
    },
    "2361":{
        "id":2361,
        "OpenTime":"2023-06-15 04:00:00",
        "CloseTime":"2023-06-22 03:59:59"
    },
    "2362":{
        "id":2362,
        "OpenTime":"2023-06-22 04:00:00",
        "CloseTime":"2023-06-29 03:59:59"
    },
    "2363":{
        "id":2363,
        "OpenTime":"2023-06-22 04:00:00",
        "CloseTime":"2023-06-29 03:59:59"
    },
    "2364":{
        "id":2364,
        "OpenTime":"2023-06-22 04:00:00",
        "CloseTime":"2023-06-29 03:59:59"
    },
    "2365":{
        "id":2365,
        "OpenTime":"2023-06-22 04:00:00",
        "CloseTime":"2023-06-29 03:59:59"
    },
    "2366":{
        "id":2366,
        "OpenTime":"2023-06-29 04:00:00",
        "CloseTime":"2023-07-06 03:59:59"
    },
    "2367":{
        "id":2367,
        "OpenTime":"2023-06-29 04:00:00",
        "CloseTime":"2023-07-06 03:59:59"
    },
    "2368":{
        "id":2368,
        "OpenTime":"2023-06-29 04:00:00",
        "CloseTime":"2023-07-06 03:59:59"
    },
    "2369":{
        "id":2369,
        "OpenTime":"2023-06-29 04:00:00",
        "CloseTime":"2023-07-06 03:59:59"
    },
    "2370":{
        "id":2370,
        "OpenTime":"2023-07-06 04:00:00",
        "CloseTime":"2023-07-13 03:59:59"
    },
    "2371":{
        "id":2371,
        "OpenTime":"2023-07-06 04:00:00",
        "CloseTime":"2023-07-13 03:59:59"
    },
    "2372":{
        "id":2372,
        "OpenTime":"2023-07-06 04:00:00",
        "CloseTime":"2023-07-13 03:59:59"
    },
    "2373":{
        "id":2373,
        "OpenTime":"2023-07-06 04:00:00",
        "CloseTime":"2023-07-13 03:59:59"
    },
    "2374":{
        "id":2374,
        "OpenTime":"2023-07-13 04:00:00",
        "CloseTime":"2023-07-20 03:59:59"
    },
    "2375":{
        "id":2375,
        "OpenTime":"2023-07-13 04:00:00",
        "CloseTime":"2023-07-20 03:59:59"
    },
    "2376":{
        "id":2376,
        "OpenTime":"2023-07-13 04:00:00",
        "CloseTime":"2023-07-20 03:59:59"
    },
    "2377":{
        "id":2377,
        "OpenTime":"2023-07-13 04:00:00",
        "CloseTime":"2023-07-20 03:59:59"
    },
    "2378":{
        "id":2378,
        "OpenTime":"2023-07-20 04:00:00",
        "CloseTime":"2023-07-27 03:59:59"
    },
    "2379":{
        "id":2379,
        "OpenTime":"2023-07-20 04:00:00",
        "CloseTime":"2023-07-27 03:59:59"
    },
    "2380":{
        "id":2380,
        "OpenTime":"2023-07-20 04:00:00",
        "CloseTime":"2023-07-27 03:59:59"
    },
    "2381":{
        "id":2381,
        "OpenTime":"2023-07-20 04:00:00",
        "CloseTime":"2023-07-27 03:59:59"
    },
    "2382":{
        "id":2382,
        "OpenTime":"2023-07-27 04:00:00",
        "CloseTime":"2023-08-03 03:59:59"
    },
    "2383":{
        "id":2383,
        "OpenTime":"2023-07-27 04:00:00",
        "CloseTime":"2023-08-03 03:59:59"
    },
    "2384":{
        "id":2384,
        "OpenTime":"2023-07-27 04:00:00",
        "CloseTime":"2023-08-03 03:59:59"
    },
    "2385":{
        "id":2385,
        "OpenTime":"2023-07-27 04:00:00",
        "CloseTime":"2023-08-03 03:59:59"
    },
    "2386":{
        "id":2386,
        "OpenTime":"2023-08-03 04:00:00",
        "CloseTime":"2023-08-10 03:59:59"
    },
    "2387":{
        "id":2387,
        "OpenTime":"2023-08-03 04:00:00",
        "CloseTime":"2023-08-10 03:59:59"
    },
    "2388":{
        "id":2388,
        "OpenTime":"2023-08-03 04:00:00",
        "CloseTime":"2023-08-10 03:59:59"
    },
    "2389":{
        "id":2389,
        "OpenTime":"2023-08-03 04:00:00",
        "CloseTime":"2023-08-10 03:59:59"
    },
    "2390":{
        "id":2390,
        "OpenTime":"2023-08-10 04:00:00",
        "CloseTime":"2023-08-17 03:59:59"
    },
    "2391":{
        "id":2391,
        "OpenTime":"2023-08-10 04:00:00",
        "CloseTime":"2023-08-17 03:59:59"
    },
    "2392":{
        "id":2392,
        "OpenTime":"2023-08-10 04:00:00",
        "CloseTime":"2023-08-17 03:59:59"
    },
    "2393":{
        "id":2393,
        "OpenTime":"2023-08-10 04:00:00",
        "CloseTime":"2023-08-17 03:59:59"
    },
    "2394":{
        "id":2394,
        "OpenTime":"2023-08-17 04:00:00",
        "CloseTime":"2023-08-24 03:59:59"
    },
    "2395":{
        "id":2395,
        "OpenTime":"2023-08-17 04:00:00",
        "CloseTime":"2023-08-24 03:59:59"
    },
    "2396":{
        "id":2396,
        "OpenTime":"2023-08-17 04:00:00",
        "CloseTime":"2023-08-24 03:59:59"
    },
    "2397":{
        "id":2397,
        "OpenTime":"2023-08-17 04:00:00",
        "CloseTime":"2023-08-24 03:59:59"
    },
    "2398":{
        "id":2398,
        "OpenTime":"2023-08-24 04:00:00",
        "CloseTime":"2023-08-31 03:59:59"
    },
    "2399":{
        "id":2399,
        "OpenTime":"2023-08-24 04:00:00",
        "CloseTime":"2023-08-31 03:59:59"
    },
    "2400":{
        "id":2400,
        "OpenTime":"2023-08-24 04:00:00",
        "CloseTime":"2023-08-31 03:59:59"
    },
    "2401":{
        "id":2401,
        "OpenTime":"2023-08-24 04:00:00",
        "CloseTime":"2023-08-31 03:59:59"
    },
    "2402":{
        "id":2402,
        "OpenTime":"2023-08-31 04:00:00",
        "CloseTime":"2023-09-07 03:59:59"
    },
    "2403":{
        "id":2403,
        "OpenTime":"2023-08-31 04:00:00",
        "CloseTime":"2023-09-07 03:59:59"
    },
    "2404":{
        "id":2404,
        "OpenTime":"2023-08-31 04:00:00",
        "CloseTime":"2023-09-07 03:59:59"
    },
    "2405":{
        "id":2405,
        "OpenTime":"2023-08-31 04:00:00",
        "CloseTime":"2023-09-07 03:59:59"
    },
    "2406":{
        "id":2406,
        "OpenTime":"2023-09-07 04:00:00",
        "CloseTime":"2023-09-14 03:59:59"
    },
    "2407":{
        "id":2407,
        "OpenTime":"2023-09-07 04:00:00",
        "CloseTime":"2023-09-14 03:59:59"
    },
    "2408":{
        "id":2408,
        "OpenTime":"2023-09-07 04:00:00",
        "CloseTime":"2023-09-14 03:59:59"
    },
    "2409":{
        "id":2409,
        "OpenTime":"2023-09-07 04:00:00",
        "CloseTime":"2023-09-14 03:59:59"
    },
    "2410":{
        "id":2410,
        "OpenTime":"2022-09-07 04:00:00",
        "CloseTime":"2022-12-08 03:59:59"
    },
    "2411":{
        "id":2411,
        "OpenTime":"2022-09-07 04:00:00",
        "CloseTime":"2022-12-08 03:59:59"
    },
    "2412":{
        "id":2412,
        "OpenTime":"2022-09-07 04:00:00",
        "CloseTime":"2022-12-08 03:59:59"
    },
    "2413":{
        "id":2413,
        "OpenTime":"2022-09-07 04:00:00",
        "CloseTime":"2022-12-08 03:59:59"
    },
    "2414":{
        "id":2414,
        "OpenTime":"2022-09-07 04:00:00",
        "CloseTime":"2023-01-05 03:59:59"
    },
    "2415":{
        "id":2415,
        "OpenTime":"2022-09-07 04:00:00",
        "CloseTime":"2023-01-05 03:59:59"
    },
    "2416":{
        "id":2416,
        "OpenTime":"2022-09-07 04:00:00",
        "CloseTime":"2023-01-05 03:59:59"
    },
    "2417":{
        "id":2417,
        "OpenTime":"2022-09-07 04:00:00",
        "CloseTime":"2023-01-05 03:59:59"
    },
    "2418":{
        "id":2418,
        "OpenTime":"2022-02-03 04:00:00",
        "CloseTime":"2023-01-19 03:59:59"
    },
    "2419":{
        "id":2419,
        "OpenTime":"2022-02-03 04:00:00",
        "CloseTime":"2023-01-19 03:59:59"
    },
    "2420":{
        "id":2420,
        "OpenTime":"2022-02-03 04:00:00",
        "CloseTime":"2023-01-19 03:59:59"
    },
    "2421":{
        "id":2421,
        "OpenTime":"2022-02-03 04:00:00",
        "CloseTime":"2023-01-19 03:59:59"
    },
    "2422":{
        "id":2422,
        "OpenTime":"2022-02-03 04:00:00",
        "CloseTime":"2023-01-13 03:59:59"
    },
    "2423":{
        "id":2423,
        "OpenTime":"2023-01-13 04:00:00",
        "CloseTime":"2023-01-14 03:59:59"
    },
    "2424":{
        "id":2424,
        "OpenTime":"2023-01-14 04:00:00",
        "CloseTime":"2023-01-15 03:59:59"
    },
    "2425":{
        "id":2425,
        "OpenTime":"2023-01-15 04:00:00",
        "CloseTime":"2023-01-16 03:59:59"
    },
    "2426":{
        "id":2426,
        "OpenTime":"2023-01-16 04:00:00",
        "CloseTime":"2023-01-17 03:59:59"
    },
    "2427":{
        "id":2427,
        "OpenTime":"2023-01-17 04:00:00",
        "CloseTime":"2023-01-18 03:59:59"
    },
    "2428":{
        "id":2428,
        "OpenTime":"2023-01-18 04:00:00",
        "CloseTime":"2023-01-19 03:59:59"
    },
    "2429":{
        "id":2429,
        "OpenTime":"2023-01-19 04:00:00",
        "CloseTime":"2023-01-20 03:59:59"
    },
    "2430":{
        "id":2430,
        "OpenTime":"2023-01-20 04:00:00",
        "CloseTime":"2023-01-21 03:59:59"
    },
    "2431":{
        "id":2431,
        "OpenTime":"2023-01-21 04:00:00",
        "CloseTime":"2023-01-22 03:59:59"
    },
    "2432":{
        "id":2432,
        "OpenTime":"2023-01-22 04:00:00",
        "CloseTime":"2023-01-23 03:59:59"
    },
    "2433":{
        "id":2433,
        "OpenTime":"2023-01-23 04:00:00",
        "CloseTime":"2023-01-24 03:59:59"
    },
    "2434":{
        "id":2434,
        "OpenTime":"2023-01-24 04:00:00",
        "CloseTime":"2023-01-25 03:59:59"
    },
    "2435":{
        "id":2435,
        "OpenTime":"2023-01-25 04:00:00",
        "CloseTime":"2023-01-26 03:59:59"
    },
    "2436":{
        "id":2436,
        "OpenTime":"2023-01-26 04:00:00",
        "CloseTime":"2023-01-27 03:59:59"
    },
    "2437":{
        "id":2437,
        "OpenTime":"2023-01-27 04:00:00",
        "CloseTime":"2023-01-28 03:59:59"
    },
    "2438":{
        "id":2438,
        "OpenTime":"2023-01-28 04:00:00",
        "CloseTime":"2023-01-29 03:59:59"
    },
    "2439":{
        "id":2439,
        "OpenTime":"2023-01-29 04:00:00",
        "CloseTime":"2023-01-30 03:59:59"
    },
    "2440":{
        "id":2440,
        "OpenTime":"2023-01-30 04:00:00",
        "CloseTime":"2023-01-31 03:59:59"
    },
    "2441":{
        "id":2441,
        "OpenTime":"2023-01-31 04:00:00",
        "CloseTime":"2023-02-01 03:59:59"
    },
    "2442":{
        "id":2442,
        "OpenTime":"2023-02-01 04:00:00",
        "CloseTime":"2023-02-02 03:59:59"
    },
    "2443":{
        "id":2443,
        "OpenTime":"2023-01-19 04:00:00",
        "CloseTime":"2023-01-26 03:59:59"
    },
    "2444":{
        "id":2444,
        "OpenTime":"2023-01-19 04:00:00",
        "CloseTime":"2023-01-26 03:59:59"
    },
    "2445":{
        "id":2445,
        "OpenTime":"2023-01-19 04:00:00",
        "CloseTime":"2023-01-26 03:59:59"
    },
    "2446":{
        "id":2446,
        "OpenTime":"2023-01-19 04:00:00",
        "CloseTime":"2023-01-26 03:59:59"
    },
    "2447":{
        "id":2447,
        "OpenTime":"2023-01-26 04:00:00",
        "CloseTime":"2023-02-02 03:59:59"
    },
    "2448":{
        "id":2448,
        "OpenTime":"2023-01-26 04:00:00",
        "CloseTime":"2023-02-02 03:59:59"
    },
    "2449":{
        "id":2449,
        "OpenTime":"2023-01-26 04:00:00",
        "CloseTime":"2023-02-02 03:59:59"
    },
    "2450":{
        "id":2450,
        "OpenTime":"2023-01-26 04:00:00",
        "CloseTime":"2023-02-02 03:59:59"
    },
    "2451":{
        "id":2451,
        "OpenTime":"2022-02-10 04:00:00",
        "CloseTime":"2023-03-02 03:59:59"
    },
    "2452":{
        "id":2452,
        "OpenTime":"2022-02-10 04:00:00",
        "CloseTime":"2023-03-02 03:59:59"
    },
    "2453":{
        "id":2453,
        "OpenTime":"2022-02-10 04:00:00",
        "CloseTime":"2023-03-02 03:59:59"
    },
    "2454":{
        "id":2454,
        "OpenTime":"2022-02-10 04:00:00",
        "CloseTime":"2023-03-02 03:59:59"
    },
    "2455":{
        "id":2455,
        "OpenTime":"2022-02-10 04:00:00",
        "CloseTime":"2023-03-02 03:59:59"
    },
    "2456":{
        "id":2456,
        "OpenTime":"2022-03-10 04:00:00",
        "CloseTime":"2023-03-16 03:59:59"
    },
    "2457":{
        "id":2457,
        "OpenTime":"2022-03-10 04:00:00",
        "CloseTime":"2023-03-16 03:59:59"
    },
    "2458":{
        "id":2458,
        "OpenTime":"2023-03-16 04:00:00",
        "CloseTime":"2023-03-23 03:59:59"
    },
    "2459":{
        "id":2459,
        "OpenTime":"2023-03-16 04:00:00",
        "CloseTime":"2023-03-23 03:59:59"
    },
    "2460":{
        "id":2460,
        "OpenTime":"2022-03-31 04:00:00",
        "CloseTime":"2023-04-13 03:59:59"
    },
    "2461":{
        "id":2461,
        "OpenTime":"2022-03-31 04:00:00",
        "CloseTime":"2023-04-13 03:59:59"
    },
    "2462":{
        "id":2462,
        "OpenTime":"2022-03-31 04:00:00",
        "CloseTime":"2023-04-13 03:59:59"
    },
    "2463":{
        "id":2463,
        "OpenTime":"2022-03-31 04:00:00",
        "CloseTime":"2023-04-13 03:59:59"
    },
    "2464":{
        "id":2464,
        "OpenTime":"2022-03-31 04:00:00",
        "CloseTime":"2023-04-13 03:59:59"
    },
    "2465":{
        "id":2465,
        "OpenTime":"2022-04-21 04:00:00",
        "CloseTime":"2023-05-04 03:59:59"
    },
    "2466":{
        "id":2466,
        "OpenTime":"2022-04-21 04:00:00",
        "CloseTime":"2023-05-04 03:59:59"
    },
    "2467":{
        "id":2467,
        "OpenTime":"2022-04-21 04:00:00",
        "CloseTime":"2023-05-04 03:59:59"
    },
    "2468":{
        "id":2468,
        "OpenTime":"2022-04-21 04:00:00",
        "CloseTime":"2023-05-04 03:59:59"
    },
    "2469":{
        "id":2469,
        "OpenTime":"2023-04-07 04:00:00",
        "CloseTime":"2023-05-25 03:59:59"
    },
    "2470":{
        "id":2470,
        "OpenTime":"2023-04-07 04:00:00",
        "CloseTime":"2023-05-25 03:59:59"
    },
    "2471":{
        "id":2471,
        "OpenTime":"2023-04-07 04:00:00",
        "CloseTime":"2023-05-25 03:59:59"
    },
    "2472":{
        "id":2472,
        "OpenTime":"2023-04-07 04:00:00",
        "CloseTime":"2023-05-25 03:59:59"
    }
}