{
    "1":{
        "id":1,
        "activeType":1,
        "textID":100,
        "reward":[
            31037,
            31016,
            78166
        ],
        "rewardNum":[
            2,
            2,
            2
        ],
        "openTime":"2023-03-09 04:00:00",
        "closeTime":"2023-03-10 03:59:59",
        "activeID":29001
    },
    "2":{
        "id":2,
        "activeType":1,
        "textID":106,
        "reward":[
            74001,
            31010,
            35008
        ],
        "rewardNum":[
            40,
            2,
            600
        ],
        "openTime":"2023-03-10 04:00:00",
        "closeTime":"2023-03-11 03:59:59",
        "activeID":29001
    },
    "3":{
        "id":3,
        "activeType":1,
        "textID":33,
        "reward":[
            74002,
            31007,
            75008,
            75014
        ],
        "rewardNum":[
            40,
            2,
            30,
            30
        ],
        "openTime":"2023-03-11 04:00:00",
        "closeTime":"2023-03-12 03:59:59",
        "activeID":29001
    },
    "4":{
        "id":4,
        "activeType":1,
        "textID":71,
        "reward":[
            70002,
            31016,
            70003
        ],
        "rewardNum":[
            3,
            2,
            5
        ],
        "openTime":"2023-03-12 04:00:00",
        "closeTime":"2023-03-13 03:59:59",
        "activeID":29001
    },
    "5":{
        "id":5,
        "activeType":2,
        "textID":0,
        "reward":[
            35008,
            31312,
            49901
        ],
        "rewardNum":[
            500,
            2,
            3
        ],
        "openTime":"2023-03-13 04:00:00",
        "closeTime":"2023-03-14 03:59:59",
        "activeID":29001
    },
    "6":{
        "id":6,
        "activeType":2,
        "textID":0,
        "reward":[
            30076,
            31312,
            49902
        ],
        "rewardNum":[
            2,
            2,
            3
        ],
        "openTime":"2023-03-14 04:00:00",
        "closeTime":"2023-03-15 03:59:59",
        "activeID":29001
    },
    "7":{
        "id":7,
        "activeType":1,
        "textID":67,
        "reward":[
            31038,
            31013,
            79002,
            79001
        ],
        "rewardNum":[
            2,
            2,
            25,
            100
        ],
        "openTime":"2023-03-15 04:00:00",
        "closeTime":"2023-03-16 03:59:59",
        "activeID":29001
    }
}