{
    "1400064": {
        "text": "",
        "id": 1400064
    },
    "1400065": {
        "text": "",
        "id": 1400065
    },
    "1400066": {
        "text": "",
        "id": 1400066
    },
    "1400067": {
        "text": "",
        "id": 1400067
    },
    "1400068": {
        "text": "",
        "id": 1400068
    },
    "1400069": {
        "text": "",
        "id": 1400069
    },
    "1400070": {
        "text": "",
        "id": 1400070
    },
    "1400071": {
        "text": "",
        "id": 1400071
    },
    "1400072": {
        "text": "",
        "id": 1400072
    },
    "1400073": {
        "text": "",
        "id": 1400073
    },
    "1400074": {
        "text": "",
        "id": 1400074
    },
    "1400075": {
        "text": "",
        "id": 1400075
    },
    "1400076": {
        "text": "",
        "id": 1400076
    },
    "1400077": {
        "text": "",
        "id": 1400077
    },
    "1400078": {
        "text": "",
        "id": 1400078
    },
    "1400079": {
        "text": "",
        "id": 1400079
    },
    "1400080": {
        "text": "",
        "id": 1400080
    },
    "1400081": {
        "text": "",
        "id": 1400081
    },
    "1400082": {
        "text": "",
        "id": 1400082
    },
    "1400083": {
        "text": "",
        "id": 1400083
    },
    "1400084": {
        "text": "",
        "id": 1400084
    },
    "1400085": {
        "text": "",
        "id": 1400085
    },
    "1400086": {
        "text": "",
        "id": 1400086
    },
    "1400087": {
        "text": "",
        "id": 1400087
    },
    "1400088": {
        "text": "",
        "id": 1400088
    },
    "1400089": {
        "text": "",
        "id": 1400089
    },
    "1400090": {
        "text": "",
        "id": 1400090
    },
    "1400091": {
        "text": "",
        "id": 1400091
    },
    "1400092": {
        "text": "",
        "id": 1400092
    },
    "1400093": {
        "text": "",
        "id": 1400093
    },
    "1400094": {
        "text": "",
        "id": 1400094
    },
    "1400095": {
        "text": "",
        "id": 1400095
    },
    "1400096": {
        "text": "",
        "id": 1400096
    },
    "1400097": {
        "text": "",
        "id": 1400097
    },
    "1400098": {
        "text": "",
        "id": 1400098
    },
    "1400099": {
        "text": "",
        "id": 1400099
    },
    "1400100": {
        "text": "",
        "id": 1400100
    },
    "1400101": {
        "text": "",
        "id": 1400101
    },
    "1400102": {
        "text": "",
        "id": 1400102
    },
    "1400103": {
        "text": "",
        "id": 1400103
    },
    "1400104": {
        "text": "",
        "id": 1400104
    },
    "1400105": {
        "text": "",
        "id": 1400105
    },
    "1400106": {
        "text": "",
        "id": 1400106
    },
    "1400107": {
        "text": "",
        "id": 1400107
    },
    "1400108": {
        "text": "",
        "id": 1400108
    },
    "1400109": {
        "text": "",
        "id": 1400109
    },
    "1400110": {
        "text": "",
        "id": 1400110
    },
    "1400111": {
        "text": "",
        "id": 1400111
    },
    "1400112": {
        "text": "",
        "id": 1400112
    },
    "1400113": {
        "text": "",
        "id": 1400113
    },
    "1400114": {
        "text": "",
        "id": 1400114
    },
    "1400115": {
        "text": "",
        "id": 1400115
    },
    "1400116": {
        "text": "",
        "id": 1400116
    },
    "1400117": {
        "text": "",
        "id": 1400117
    },
    "1400118": {
        "text": "",
        "id": 1400118
    },
    "1400119": {
        "text": "",
        "id": 1400119
    },
    "1400120": {
        "text": "",
        "id": 1400120
    },
    "1400121": {
        "text": "",
        "id": 1400121
    },
    "1400122": {
        "text": "",
        "id": 1400122
    },
    "1400123": {
        "text": "",
        "id": 1400123
    },
    "1400124": {
        "text": "",
        "id": 1400124
    },
    "1400125": {
        "text": "",
        "id": 1400125
    },
    "1400126": {
        "text": "",
        "id": 1400126
    },
    "1400127": {
        "text": "",
        "id": 1400127
    },
    "1400128": {
        "text": "",
        "id": 1400128
    },
    "1400129": {
        "text": "",
        "id": 1400129
    },
    "1400130": {
        "text": "",
        "id": 1400130
    },
    "1400131": {
        "text": "",
        "id": 1400131
    },
    "1400132": {
        "text": "",
        "id": 1400132
    },
    "1400133": {
        "text": "",
        "id": 1400133
    },
    "1400134": {
        "text": "",
        "id": 1400134
    },
    "1400135": {
        "text": "",
        "id": 1400135
    },
    "1400136": {
        "text": "",
        "id": 1400136
    },
    "1400137": {
        "text": "",
        "id": 1400137
    },
    "1400138": {
        "text": "",
        "id": 1400138
    },
    "1400139": {
        "text": "",
        "id": 1400139
    },
    "1400140": {
        "text": "",
        "id": 1400140
    },
    "1400141": {
        "text": "",
        "id": 1400141
    },
    "1400142": {
        "text": "",
        "id": 1400142
    },
    "1400143": {
        "text": "",
        "id": 1400143
    },
    "1400144": {
        "text": "",
        "id": 1400144
    },
    "1400145": {
        "text": "",
        "id": 1400145
    },
    "1400146": {
        "text": "",
        "id": 1400146
    },
    "1400147": {
        "text": "",
        "id": 1400147
    },
    "1400148": {
        "text": "",
        "id": 1400148
    },
    "1400149": {
        "text": "",
        "id": 1400149
    },
    "1400150": {
        "text": "",
        "id": 1400150
    },
    "1400151": {
        "text": "",
        "id": 1400151
    },
    "1400152": {
        "text": "",
        "id": 1400152
    },
    "1400153": {
        "text": "",
        "id": 1400153
    },
    "1400154": {
        "text": "",
        "id": 1400154
    },
    "1400155": {
        "text": "",
        "id": 1400155
    },
    "1400156": {
        "text": "",
        "id": 1400156
    },
    "1400157": {
        "text": "",
        "id": 1400157
    },
    "1400158": {
        "text": "",
        "id": 1400158
    },
    "1400159": {
        "text": "",
        "id": 1400159
    },
    "1400160": {
        "text": "",
        "id": 1400160
    },
    "1400161": {
        "text": "",
        "id": 1400161
    },
    "1400162": {
        "text": "",
        "id": 1400162
    },
    "1400163": {
        "text": "",
        "id": 1400163
    },
    "1400164": {
        "text": "",
        "id": 1400164
    },
    "1400165": {
        "text": "",
        "id": 1400165
    },
    "1400166": {
        "text": "",
        "id": 1400166
    },
    "1400167": {
        "text": "",
        "id": 1400167
    },
    "1400168": {
        "text": "",
        "id": 1400168
    },
    "1400169": {
        "text": "",
        "id": 1400169
    },
    "1400170": {
        "text": "",
        "id": 1400170
    },
    "1400171": {
        "text": "",
        "id": 1400171
    },
    "1400172": {
        "text": "",
        "id": 1400172
    },
    "1400173": {
        "text": "",
        "id": 1400173
    },
    "1400174": {
        "text": "",
        "id": 1400174
    },
    "1400175": {
        "text": "",
        "id": 1400175
    },
    "1400176": {
        "text": "",
        "id": 1400176
    },
    "1400177": {
        "text": "",
        "id": 1400177
    },
    "1400178": {
        "text": "",
        "id": 1400178
    },
    "1400179": {
        "text": "",
        "id": 1400179
    },
    "1400180": {
        "text": "",
        "id": 1400180
    },
    "1400181": {
        "text": "",
        "id": 1400181
    },
    "1400182": {
        "text": "",
        "id": 1400182
    },
    "1400183": {
        "text": "",
        "id": 1400183
    },
    "1400184": {
        "text": "",
        "id": 1400184
    },
    "1400185": {
        "text": "",
        "id": 1400185
    },
    "1400186": {
        "text": "",
        "id": 1400186
    },
    "1400187": {
        "text": "",
        "id": 1400187
    },
    "1400188": {
        "text": "",
        "id": 1400188
    },
    "1400189": {
        "text": "",
        "id": 1400189
    },
    "1400190": {
        "text": "",
        "id": 1400190
    },
    "1400191": {
        "text": "",
        "id": 1400191
    },
    "1400192": {
        "text": "",
        "id": 1400192
    },
    "1400193": {
        "text": "",
        "id": 1400193
    },
    "1400194": {
        "text": "",
        "id": 1400194
    },
    "1400195": {
        "text": "",
        "id": 1400195
    },
    "1400196": {
        "text": "",
        "id": 1400196
    },
    "1400197": {
        "text": "",
        "id": 1400197
    },
    "1400198": {
        "text": "",
        "id": 1400198
    },
    "1400199": {
        "text": "",
        "id": 1400199
    },
    "1400200": {
        "text": "",
        "id": 1400200
    },
    "1400201": {
        "text": "",
        "id": 1400201
    },
    "1400202": {
        "text": "",
        "id": 1400202
    },
    "1400203": {
        "text": "",
        "id": 1400203
    },
    "1400204": {
        "text": "",
        "id": 1400204
    },
    "1400205": {
        "text": "",
        "id": 1400205
    },
    "1400206": {
        "text": "",
        "id": 1400206
    },
    "1400207": {
        "text": "",
        "id": 1400207
    },
    "1400208": {
        "text": "",
        "id": 1400208
    },
    "1400209": {
        "text": "",
        "id": 1400209
    },
    "1400210": {
        "text": "",
        "id": 1400210
    },
    "1400211": {
        "text": "",
        "id": 1400211
    },
    "1400212": {
        "text": "",
        "id": 1400212
    },
    "1400213": {
        "text": "",
        "id": 1400213
    },
    "1400214": {
        "text": "",
        "id": 1400214
    },
    "1400215": {
        "text": "",
        "id": 1400215
    },
    "1400216": {
        "text": "",
        "id": 1400216
    },
    "1400217": {
        "text": "",
        "id": 1400217
    },
    "1400218": {
        "text": "",
        "id": 1400218
    },
    "1400219": {
        "text": "",
        "id": 1400219
    },
    "1400220": {
        "text": "",
        "id": 1400220
    },
    "1400221": {
        "text": "",
        "id": 1400221
    },
    "1400222": {
        "text": "",
        "id": 1400222
    },
    "1400223": {
        "text": "",
        "id": 1400223
    },
    "1400224": {
        "text": "",
        "id": 1400224
    },
    "1400225": {
        "text": "",
        "id": 1400225
    },
    "1400226": {
        "text": "",
        "id": 1400226
    },
    "1400227": {
        "text": "",
        "id": 1400227
    },
    "1400228": {
        "text": "",
        "id": 1400228
    },
    "1400229": {
        "text": "",
        "id": 1400229
    },
    "1400230": {
        "text": "",
        "id": 1400230
    },
    "1400231": {
        "text": "",
        "id": 1400231
    },
    "1400232": {
        "text": "",
        "id": 1400232
    },
    "1400233": {
        "text": "",
        "id": 1400233
    },
    "1400234": {
        "text": "",
        "id": 1400234
    },
    "1400235": {
        "text": "",
        "id": 1400235
    },
    "1400236": {
        "text": "",
        "id": 1400236
    },
    "1400237": {
        "text": "",
        "id": 1400237
    },
    "1400238": {
        "text": "",
        "id": 1400238
    },
    "1400239": {
        "text": "",
        "id": 1400239
    },
    "1400240": {
        "text": "",
        "id": 1400240
    },
    "1400001": {
        "text": "",
        "id": 1400001
    },
    "1400002": {
        "text": "",
        "id": 1400002
    },
    "1400003": {
        "text": "",
        "id": 1400003
    },
    "1400004": {
        "text": "",
        "id": 1400004
    },
    "1400005": {
        "text": "",
        "id": 1400005
    },
    "1400006": {
        "text": "",
        "id": 1400006
    },
    "1400007": {
        "text": "",
        "id": 1400007
    },
    "1400008": {
        "text": "",
        "id": 1400008
    },
    "1400009": {
        "text": "",
        "id": 1400009
    },
    "1400010": {
        "text": "",
        "id": 1400010
    },
    "1400011": {
        "text": "",
        "id": 1400011
    },
    "1400012": {
        "text": "",
        "id": 1400012
    },
    "1400013": {
        "text": "",
        "id": 1400013
    },
    "1400014": {
        "text": "",
        "id": 1400014
    },
    "1400015": {
        "text": "",
        "id": 1400015
    },
    "1400016": {
        "text": "",
        "id": 1400016
    },
    "1400017": {
        "text": "",
        "id": 1400017
    },
    "1400018": {
        "text": "",
        "id": 1400018
    },
    "1400019": {
        "text": "",
        "id": 1400019
    },
    "1400020": {
        "text": "",
        "id": 1400020
    },
    "1400021": {
        "text": "",
        "id": 1400021
    },
    "1400022": {
        "text": "",
        "id": 1400022
    },
    "1400023": {
        "text": "",
        "id": 1400023
    },
    "1400024": {
        "text": "",
        "id": 1400024
    },
    "1400025": {
        "text": "",
        "id": 1400025
    },
    "1400026": {
        "text": "",
        "id": 1400026
    },
    "1400027": {
        "text": "",
        "id": 1400027
    },
    "1400028": {
        "text": "",
        "id": 1400028
    },
    "1400029": {
        "text": "",
        "id": 1400029
    },
    "1400030": {
        "text": "",
        "id": 1400030
    },
    "1400031": {
        "text": "",
        "id": 1400031
    },
    "1400032": {
        "text": "",
        "id": 1400032
    },
    "1400033": {
        "text": "",
        "id": 1400033
    },
    "1400034": {
        "text": "",
        "id": 1400034
    },
    "1400035": {
        "text": "",
        "id": 1400035
    },
    "1400036": {
        "text": "",
        "id": 1400036
    },
    "1400037": {
        "text": "",
        "id": 1400037
    },
    "1400038": {
        "text": "",
        "id": 1400038
    },
    "1400039": {
        "text": "",
        "id": 1400039
    },
    "1400040": {
        "text": "",
        "id": 1400040
    },
    "1400041": {
        "text": "",
        "id": 1400041
    },
    "1400042": {
        "text": "",
        "id": 1400042
    },
    "1400043": {
        "text": "",
        "id": 1400043
    },
    "1400044": {
        "text": "",
        "id": 1400044
    },
    "1400045": {
        "text": "",
        "id": 1400045
    },
    "1400046": {
        "text": "",
        "id": 1400046
    },
    "1400047": {
        "text": "",
        "id": 1400047
    },
    "1400048": {
        "text": "",
        "id": 1400048
    },
    "1400049": {
        "text": "",
        "id": 1400049
    },
    "1400050": {
        "text": "",
        "id": 1400050
    },
    "1400051": {
        "text": "",
        "id": 1400051
    },
    "1400052": {
        "text": "",
        "id": 1400052
    },
    "1400053": {
        "text": "",
        "id": 1400053
    },
    "1400054": {
        "text": "",
        "id": 1400054
    },
    "1400055": {
        "text": "",
        "id": 1400055
    },
    "1400056": {
        "text": "",
        "id": 1400056
    },
    "1400057": {
        "text": "",
        "id": 1400057
    },
    "1400058": {
        "text": "",
        "id": 1400058
    },
    "1400059": {
        "text": "",
        "id": 1400059
    },
    "1400060": {
        "text": "",
        "id": 1400060
    },
    "1400061": {
        "text": "",
        "id": 1400061
    },
    "1400062": {
        "text": "",
        "id": 1400062
    },
    "1400063": {
        "text": "",
        "id": 1400063
    }
}